snakai/__init__.py
snakai/run.py
snakai/snake_state_machine.py
snakai/snake_state_machine_util.py
snakai/snake_state_machine_util_test.py
snakai/curses_game/__init__.py
snakai/curses_game/exe.py
snakai/curses_game/ui.py
snakai/strategy/__init__.py
snakai/strategy/base.py
snakai/strategy/manual.py
snakai/strategy/rule_based.py
snakai/strategy/qlearning/__init__.py
snakai/strategy/qlearning/action_translator.py
snakai/strategy/qlearning/qtable.py
snakai/strategy/qlearning/reward.py
snakai/strategy/qlearning/state_translator.py
snakai/strategy/qlearning/strategy.py
snakai/strategy/qlearning/train.py
snakai/util/__init__.py
snakai/util/logger.py
snakai-1.1.dist-info/LICENSE
snakai-1.1.dist-info/METADATA
snakai-1.1.dist-info/WHEEL
snakai-1.1.dist-info/entry_points.txt
snakai-1.1.dist-info/top_level.txt
snakai-1.1.dist-info/RECORD
