Metadata-Version: 2.1
Name: snakai
Version: 1.1
Summary: snake with ai
Home-page: https://github.com/fseasy/snakai
Author: fishshrimp
Author-email: readonlyfile@hotmail.com
License: UNKNOWN
Platform: UNKNOWN
Classifier: Programming Language :: Python :: 3
Classifier: License :: OSI Approved :: Apache Software License
Requires-Python: >=3.6
Requires-Dist: numpy
Requires-Dist: tqdm
